infocircle/__init__.py
infocircle/infocircle.py
infocircle-2.0.1.dist-info/LICENSE
infocircle-2.0.1.dist-info/METADATA
infocircle-2.0.1.dist-info/WHEEL
infocircle-2.0.1.dist-info/entry_points.txt
infocircle-2.0.1.dist-info/top_level.txt
infocircle-2.0.1.dist-info/RECORD
