Metadata-Version: 2.1
Name: infocircle
Version: 2.0.1
Summary: ROBI CIRCLE INFORMATION FINDER
Home-page: https://github.com/AKXVAU
Author: AKXVAU
Author-email: admin@itzakx.com
License: MIT
Keywords: AKXVAU
Classifier: Development Status :: 4 - Beta
Classifier: Intended Audience :: Developers
Classifier: Topic :: Software Development :: Libraries :: Python Modules
Classifier: License :: OSI Approved :: MIT License
Classifier: Programming Language :: Python :: 3
Classifier: Operating System :: OS Independent
Classifier: Environment :: Console
Requires-Python: >=3.9
License-File: LICENSE
Requires-Dist: lolcat
Requires-Dist: requests
